telliot_core/__init__.py
telliot_core/api.py
telliot_core/asset_registry.py
telliot_core/directory.py
telliot_core/logs.py
telliot_core/apps/__init__.py
telliot_core/apps/app.py
telliot_core/apps/config.py
telliot_core/apps/core.py
telliot_core/apps/session_manager.py
telliot_core/apps/telliot_config.py
telliot_core/cli/__init__.py
telliot_core/cli/main.py
telliot_core/cli/utils.py
telliot_core/cli/commands/__init__.py
telliot_core/cli/commands/account.py
telliot_core/cli/commands/config.py
telliot_core/cli/commands/listen.py
telliot_core/cli/commands/read.py
telliot_core/contract/__init__.py
telliot_core/contract/contract.py
telliot_core/contract/listener.py
telliot_core/data/__init__.py
telliot_core/data/assets.json
telliot_core/data/contract_directory.json
telliot_core/data/abi/diva-oracle-tellor-abi.json
telliot_core/data/abi/diva-protocol-abi.json
telliot_core/data/abi/fuse-token-abi.json
telliot_core/data/abi/tellor-governance-abi.json
telliot_core/data/abi/tellor-mesosphere-abi.json
telliot_core/data/abi/tellor360-autopay-abi.json
telliot_core/data/abi/tellor360-oracle-abi.json
telliot_core/data/abi/tellor360-playground.json
telliot_core/data/abi/tellorflex-autopay-abi.json
telliot_core/data/abi/tellorflex-oracle-abi.json
telliot_core/data/abi/tellorx-governance-abi.json
telliot_core/data/abi/tellorx-lens-abi.json
telliot_core/data/abi/tellorx-master-abi.json
telliot_core/data/abi/tellorx-oracle-abi.json
telliot_core/data/abi/tellorx-treasury-abi.json
telliot_core/data/abi/trb-token-abi.json
telliot_core/gas/__init__.py
telliot_core/gas/legacy_gas.py
telliot_core/model/__init__.py
telliot_core/model/api_keys.py
telliot_core/model/asset.py
telliot_core/model/base.py
telliot_core/model/chain.py
telliot_core/model/endpoints.py
telliot_core/model/registry.py
telliot_core/model/tokens.py
telliot_core/reporters/__init__.py
telliot_core/tellor/__init__.py
telliot_core/tellor/tellor360/autopay.py
telliot_core/tellor/tellor360/oracle.py
bctsag_telliotcore-1.0.1.dist-info/METADATA
bctsag_telliotcore-1.0.1.dist-info/WHEEL
bctsag_telliotcore-1.0.1.dist-info/entry_points.txt
bctsag_telliotcore-1.0.1.dist-info/top_level.txt
bctsag_telliotcore-1.0.1.dist-info/RECORD
